MANIFEST.in
README.md
setup.cfg
setup.py
anet_tools/__init__.py
anet_tools/anet_db.py
anet_tools/augmentation.py
anet_tools/feature_extractor.py
anet_tools.egg-info/PKG-INFO
anet_tools.egg-info/SOURCES.txt
anet_tools.egg-info/dependency_links.txt
anet_tools.egg-info/not-zip-safe
anet_tools.egg-info/requires.txt
anet_tools.egg-info/top_level.txt
anet_tools/data/__init__.py
anet_tools/data/motions/__init__.py
anet_tools/features/__init__.py
anet_tools/features/data.py
anet_tools/features/inception.py
anet_tools/features/resnet.py
anet_tools/features/flownet2/__init__.py
anet_tools/features/flownet2/convert.py
anet_tools/features/flownet2/datasets.py
anet_tools/features/flownet2/losses.py
anet_tools/features/flownet2/main.py
anet_tools/features/flownet2/models.py
anet_tools/features/flownet2/run_a_pair.py
anet_tools/features/flownet2/networks/FlowNetC.py
anet_tools/features/flownet2/networks/FlowNetFusion.py
anet_tools/features/flownet2/networks/FlowNetS.py
anet_tools/features/flownet2/networks/FlowNetSD.py
anet_tools/features/flownet2/networks/__init__.py
anet_tools/features/flownet2/networks/submodules.py
anet_tools/features/flownet2/networks/channelnorm_package/__init__.py
anet_tools/features/flownet2/networks/channelnorm_package/channelnorm.py
anet_tools/features/flownet2/networks/channelnorm_package/channelnorm_cuda.cc
anet_tools/features/flownet2/networks/channelnorm_package/channelnorm_kernel.cu
anet_tools/features/flownet2/networks/channelnorm_package/channelnorm_kernel.cuh
anet_tools/features/flownet2/networks/channelnorm_package/setup.py
anet_tools/features/flownet2/networks/correlation_package/__init__.py
anet_tools/features/flownet2/networks/correlation_package/correlation.py
anet_tools/features/flownet2/networks/correlation_package/correlation_cuda.cc
anet_tools/features/flownet2/networks/correlation_package/correlation_cuda_kernel.cu
anet_tools/features/flownet2/networks/correlation_package/correlation_cuda_kernel.cuh
anet_tools/features/flownet2/networks/correlation_package/setup.py
anet_tools/features/flownet2/networks/resample2d_package/__init__.py
anet_tools/features/flownet2/networks/resample2d_package/resample2d.py
